{
    "views": {
        "edit": {
            "structure": {
                "rows": [
                    {
                        "columns": [
                            {
                                "name": "",
                                "class_name": "col-sm-6",
                                "items": [
                                    {
                                        "group": {
                                            "name": "comment Detail",
                                            "unique_name": "comment_detail",
                                            "has_title": 1,
                                            "user_right": null,
                                            "hide_on_new": null,
                                            "fields": [
                                                "comment",
                                                "subset_id",
                                                "record_id",
                                                "parent_id"
                                            ]
                                        }
                                    }
                                ]
                            },
                            {
                                "name": "",
                                "class_name": "col-sm-6",
                                "items": [
                                    {
                                        "group": {
                                            "name": "Other Detail",
                                            "unique_name": "other_detail",
                                            "has_title": 1,
                                            "user_right": null,
                                            "hide_on_new": null,
                                            "fields": [
                                                "modified_by",
                                                "date_modified",
                                                "created_by",
                                                "date_created",
                                                "id"
                                            ]
                                        }
                                    }
                                ]
                            }
                        ]
                    }
                ]
            },
            "ommitted": [
            ]
        },
        "table": {
            "fields": [
                "subset_id",
                "record_id",
                "comment"
            ],
            "has_label": [
                "subset_id",
                "record_id",
                "comment"
            ]
        }
    },
    "rights": {
        "tab": [
        ],
        "group": [
        ],
        "field": [
        ]
    },
    "customhtmls": [
    ],
    "fields": [
        {
            "dropdown_filter": "0",
            "nullable": "0",
            "name": "id",
            "html_type": "text",
            "mysql_type": "int",
            "view_side": "both",
            "index": "",
            "id_name": "",
            "class_name": "",
            "default_value": "",
            "size": "",
            "readonly": "",
            "format_value": "",
            "parameters": {
                "general": [
                ],
                "source": [
                ],
                "save": {
                    "index": ""
                },
                "media": [
                ],
                "payment": [
                ]
            }
        },
        {
            "dropdown_filter": "1",
            "nullable": "0",
            "name": "subset_id",
            "html_type": "select",
            "mysql_type": "int",
            "view_side": "both",
            "index": "",
            "id_name": "",
            "class_name": "",
            "default_value": "",
            "size": "",
            "readonly": "",
            "format_value": "",
            "parameters": {
                "general": [
                ],
                "source": {
                    "data_source": "db_table",
                    "join_field": "id",
                    "display_field": [
                        "title"
                    ],
                    "join_table_name": "system_subsets"
                },
                "save": {
                    "index": ""
                },
                "media": [
                ],
                "payment": [
                ]
            }
        },
        {
            "dropdown_filter": "1",
            "nullable": "0",
            "name": "record_id",
            "html_type": "text",
            "mysql_type": "int",
            "view_side": "both",
            "index": "",
            "id_name": "",
            "class_name": "",
            "default_value": "",
            "size": "",
            "readonly": "",
            "format_value": "",
            "parameters": {
                "general": [
                ],
                "source": [
                ],
                "save": {
                    "index": ""
                },
                "media": [
                ],
                "payment": [
                ]
            }
        },
        {
            "dropdown_filter": "0",
            "nullable": "1",
            "name": "parent_id",
            "html_type": "select",
            "mysql_type": "int",
            "view_side": "both",
            "index": "",
            "id_name": "",
            "class_name": "",
            "default_value": "",
            "size": "",
            "readonly": "",
            "format_value": "",
            "parameters": {
                "general": [
                ],
                "source": {
                    "data_source": "db_table",
                    "join_field": "id",
                    "display_field": [
                        "comment"
                    ],
                    "join_table_name": "notification_comments"
                },
                "save": {
                    "index": ""
                },
                "media": [
                ],
                "payment": [
                ]
            }
        },
        {
            "dropdown_filter": "1",
            "nullable": "1",
            "name": "comment",
            "html_type": "textarea",
            "mysql_type": "varchar",
            "view_side": "both",
            "index": "",
            "id_name": "",
            "class_name": "",
            "default_value": "",
            "size": "",
            "readonly": "",
            "format_value": "",
            "parameters": {
                "general": {
                    "col": "",
                    "row": ""
                },
                "source": [
                ],
                "save": {
                    "index": ""
                },
                "media": [
                ],
                "payment": [
                ]
            }
        },
        {
            "dropdown_filter": "0",
            "nullable": "0",
            "name": "created_by",
            "html_type": "text",
            "mysql_type": "int",
            "view_side": "both",
            "index": "",
            "id_name": "",
            "class_name": "",
            "default_value": "",
            "size": "",
            "readonly": "",
            "format_value": "",
            "parameters": {
                "general": [
                ],
                "source": [
                ],
                "save": {
                    "index": ""
                },
                "media": [
                ],
                "payment": [
                ]
            }
        },
        {
            "dropdown_filter": "0",
            "nullable": "0",
            "name": "date_created",
            "html_type": "datetime",
            "mysql_type": "datetime",
            "view_side": "both",
            "index": "",
            "id_name": "",
            "class_name": "",
            "default_value": "",
            "size": "",
            "readonly": "",
            "format_value": "",
            "parameters": {
                "general": [
                ],
                "source": [
                ],
                "save": {
                    "index": ""
                },
                "media": [
                ],
                "payment": [
                ]
            }
        },
        {
            "dropdown_filter": "0",
            "nullable": "0",
            "name": "modified_by",
            "html_type": "text",
            "mysql_type": "int",
            "view_side": "both",
            "index": "",
            "id_name": "",
            "class_name": "",
            "default_value": "",
            "size": "",
            "readonly": "",
            "format_value": "",
            "parameters": {
                "general": [
                ],
                "source": [
                ],
                "save": {
                    "index": ""
                },
                "media": [
                ],
                "payment": [
                ]
            }
        },
        {
            "dropdown_filter": "0",
            "nullable": "0",
            "name": "date_modified",
            "html_type": "datetime",
            "mysql_type": "datetime",
            "view_side": "both",
            "index": "",
            "id_name": "",
            "class_name": "",
            "default_value": "",
            "size": "",
            "readonly": "",
            "format_value": "",
            "parameters": {
                "general": [
                ],
                "source": [
                ],
                "save": {
                    "index": ""
                },
                "media": [
                ],
                "payment": [
                ]
            }
        }
    ],
    "primarykey": "id",
    "table_name": "notification_comments",
    "table_alias": "nc",
    "foreignkey": "",
    "renamedfields": "",
    "main_fields": [
        "id"
    ],
    "main_view": "table",
    "has_view": "1",
    "tie_field": "0",
    "email_on_new": "0",
    "email_on_edit": "0",
    "email_on_delete": "0",
    "subset_name": "comments",
    "right_field": "",
    "query": {
        "from": {
            "table": "Notification\\Comments\\Code\\Tables\\Comments",
            "alias": "nc",
            "name": "#__notification_comments"
        },
        "select": [
            "nc.id",
            "nc.subset_id",
            "ss.title AS subset_id_title",
            "nc.record_id",
            "nc.parent_id",
            "nc_2445.comment AS parent_id_comment",
            "nc.comment",
            "nc.created_by",
            "nc.date_created",
            "nc.modified_by",
            "nc.date_modified"
        ],
        "leftjoin": [
            {
                "table": "System\\Subsets\\Code\\Tables\\Subsets",
                "alias": "ss",
                "name": "#__system_subsets",
                "on": "nc.subset_id = ss.id"
            },
            {
                "table": "Notification\\Comments\\Code\\Tables\\Comments",
                "alias": "nc_2445",
                "name": "#__notification_comments",
                "on": "nc.parent_id = nc_2445.id"
            }
        ]
    }
}